onegov.pay-0.3.5-py3.6-nspkg.pth
onegov/pay/.gitignore
onegov/pay/__init__.py
onegov/pay/errors.py
onegov/pay/integration.py
onegov/pay/upgrade.py
onegov/pay/utils.py
onegov/pay/assets/js/stripe.js
onegov/pay/collections/__init__.py
onegov/pay/collections/payable.py
onegov/pay/collections/payment.py
onegov/pay/collections/payment_provider.py
onegov/pay/models/__init__.py
onegov/pay/models/payable.py
onegov/pay/models/payment.py
onegov/pay/models/payment_provider.py
onegov/pay/models/payment_providers/__init__.py
onegov/pay/models/payment_providers/stripe.py
onegov/pay/tests/conftest.py
onegov/pay/tests/test_collections.py
onegov/pay/tests/test_integration.py
onegov/pay/tests/test_models.py
onegov/pay/tests/test_stripe.py
onegov/pay/tests/test_utils.py
onegov.pay-0.3.5.dist-info/METADATA
onegov.pay-0.3.5.dist-info/WHEEL
onegov.pay-0.3.5.dist-info/entry_points.txt
onegov.pay-0.3.5.dist-info/namespace_packages.txt
onegov.pay-0.3.5.dist-info/top_level.txt
onegov.pay-0.3.5.dist-info/RECORD
