Metadata-Version: 2.1
Name: onegov.pay
Version: 0.3.5
Summary: Payments for OneGov Cloud.
Home-page: http://github.com/OneGov/onegov.pay
Author: Seantis GmbH
Author-email: info@seantis.ch
License: GPLv2
Platform: any
Classifier: Intended Audience :: Developers
Classifier: Programming Language :: Python :: 3 :: Only
Classifier: Programming Language :: Python :: 3.6
Classifier: Programming Language :: Python :: 3.7
Classifier: Topic :: Software Development :: Libraries :: Python Modules
Classifier: License :: OSI Approved :: GNU General Public License v2 (GPLv2)
Requires-Python: >=3.6
Requires-Dist: more.webassets
Requires-Dist: onegov.core (>=0.4.0)
Requires-Dist: purl
Requires-Dist: requests
Requires-Dist: stripe (>=1.77.0)
Provides-Extra: test
Requires-Dist: coverage; extra == 'test'
Requires-Dist: onegov-testing; extra == 'test'
Requires-Dist: pytest; extra == 'test'
Requires-Dist: requests-mock; extra == 'test'
